Workbook

Sheet Matriz de Riesgos
B1: MATRIZ DE RIESGOS ASOCIADOS A DISTRIBUIDORA NORTE | I1: ANÁLISIS Y EVALUACIÓN DE RIESGOS
B3: ETAPA | C3: ACTIVIDAD / PROCESO | D3: ACTOR | E3: RECURSO INVOLUCRADO | F3: ORIGEN DEL RIESGO | G3: DESCRIPCIÓN DEL RIESGO | H3: VULNERABILIDAD | I3: PROBABILIDAD | J3: DESCRIPCIÓN DE PROBABILIDAD | K3: JUSTIFICACIÓN DE PROBABILIDAD | L3: IMPACTO | M3: DESCRIPCIÓN DEL IMPACTO | N3: JUSTIFICACIÓN DEL IMPACTO | O3: SEVERIDAD DEL RIESGO
B5: Compra a proveedor | C5: Recepción de comprobante de compra | D5: Proveedor Vendedor | E5: Teléfono móvil WhatsApp Email | F5: Apertura de archivo malicioso recibido como comprobante de compra. | G5: Compromiso de información por malware | H5: Falta de verificación de archivos adjuntos antes de su apertura | I5: 2 | J5: =IF(I5="","",IF(I5=1,"Muy improbable",IF(I5=2,"Improbable",IF(I5=3,"Moderado",IF(I5=4,"Probable",IF(I5=5,"Casi certeza","")))))) -> Improbable | K5: La recepción de archivos de proveedores es habitual, pero para que ocurra el riesgo el archivo debe ser malicioso y ser abierto por el vendedor. | L5: 4 | M5: Puede afectar la confidencialidad, integridad o disponibilidad de información del negocio. | N5: La información afectada puede ser necesaria para pedidos, clientes, proveedores o comprobantes del negocio. | O5: {=IF(OR(I5="",L5=""),"",INDEX('Estimación de Severidad'!$O$11:$O$35,MATCH(1,('Estimación de Severidad'!$L$11:$L$35=I5)*('Estimación de Severidad'!$M$11:$M$35=L5),0)))} -> Alto
B11: Compra a proveedor | C11: Recepción de comprobante de compra | D11: Proveedor Vendedor | E11: Teléfono móvil WhatsApp Email | F11: Apertura de un archivo malicioso recibido como comprobante de compra | G11: Interrupción de las operaciones por malware | H11: Falta de verificación de archivos adjuntos antes de su apertura | I11: 2 | J11: =IF(I11="","",IF(I11=1,"Muy improbable",IF(I5=2,"Improbable",IF(I11=3,"Moderado",IF(I5=4,"Probable",IF(I11=5,"Casi certeza","")))))) -> Improbable | K11: El riesgo requiere la apertura y ejecución de un archivo malicioso que llegue a afectar el funcionamiento del dispositivo. | L11: 2 | M11: Puede impedir temporalmente el uso de dispositivos y afectar tareas comerciales. | N11: La indisponibilidad de un dispositivo puede retrasar comunicaciones y tareas habituales de la distribuidora. | O11: {=IF(OR(I11="",L11=""),"",INDEX('Estimación de Severidad'!$O$11:$O$35,MATCH(1,('Estimación de Severidad'!$L$11:$L$35=I11)*('Estimación de Severidad'!$M$11:$M$35=L11),0)))} -> Bajo
B16: Compra a proveedor | C16: Recepción de comprobante de compra | D16: Proveedor Vendedor | E16: Teléfono móvil WhatsApp Email | F16: Apertura de un archivo malicioso recibido como comprobante de compra | G16: Pérdidas financieras por malware | H16: Falta de verificación de archivos adjuntos antes de su apertura | I16: 2 | J16: =IF(I16="","",IF(I16=1,"Muy improbable",IF(I16=2,"Improbable",IF(I16=3,"Moderado",IF(I16=4,"Probable",IF(I16=5,"Casi certeza","")))))) -> Improbable | K16: Para producir una pérdida económica, el malware tendría que comprometer además credenciales o aplicaciones relacionadas con los cobros. | L16: 2 | M16: Puede generar accesos indebidos a cuentas o movimientos no autorizados. | N16: El acceso a cuentas o credenciales puede generar pérdidas económicas directas. | O16: {=IF(OR(I16="",L16=""),"",INDEX('Estimación de Severidad'!$O$11:$O$35,MATCH(1,('Estimación de Severidad'!$L$11:$L$35=I16)*('Estimación de Severidad'!$M$11:$M$35=L16),0)))} -> Bajo
B22: Comunicación con proveedor | C22: Solicitar datos personales | D22: Proveedor Vendedor | E22: Teléfono móvil WhatsApp | F22: Recepción de mensaje fraudulento que suplanta la identidad del proveedor | G22: Phishing | H22: Falta de validación de la identidad del proveedor | I22: 4 | J22: =IF(I22="","",IF(I22=1,"Muy improbable",IF(I22=2,"Improbable",IF(I22=3,"Moderado",IF(I22=4,"Probable",IF(I22=5,"Casi certeza","")))))) -> Probable | K22: La comunicación habitual mediante WhatsApp facilita la recepción de mensajes que podrían intentar hacerse pasar por un proveedor real. | L22: 3 | M22: Puede provocar entrega de información sensible o credenciales a terceros. | N22: La entrega de datos sensibles puede comprometer cuentas y facilitar otros accesos fraudulentos. | O22: {=IF(OR(I22="",L22=""),"",INDEX('Estimación de Severidad'!$O$11:$O$35,MATCH(1,('Estimación de Severidad'!$L$11:$L$35=I22)*('Estimación de Severidad'!$M$11:$M$35=L22),0)))} -> Alto
B27: Comunicación con proveedor | C27: Solicitar datos personales | D27: Proveedor Vendedor | E27: Teléfono móvil WhatsApp | F27: Recepción de mensaje fraudulento que suplanta la identidad del proveedor | G27: Acceso no autorizado | H27: Falta de validación de la identidad del proveedor | I27: 3 | J27: =IF(I27="","",IF(I27=1,"Muy improbable",IF(I27=2,"Improbable",IF(I27=3,"Moderado",IF(I27=4,"Probable",IF(I27=5,"Casi certeza","")))))) -> Moderado | K27: La entrega de datos o credenciales ante un mensaje fraudulento podría permitir el acceso indebido a cuentas o información del negocio. | L27: 3 | M27: Puede permitir el ingreso indebido a cuentas o información del negocio. | N27: Un tercero podría visualizar, modificar o utilizar información sin permiso. | O27: {=IF(OR(I27="",L27=""),"",INDEX('Estimación de Severidad'!$O$11:$O$35,MATCH(1,('Estimación de Severidad'!$L$11:$L$35=I27)*('Estimación de Severidad'!$M$11:$M$35=L27),0)))} -> Alto
B32: Comunicación con proveedor | C32: Solicitar datos personales | D32: Proveedor Vendedor | E32: Teléfono móvil WhatsApp | F32: Recepción de mensaje fraudulento que suplanta la identidad del proveedor | G32: Suplantación de identidad | H32: Falta de validación de la identidad del proveedor | I32: 4 | J32: =IF(I32="","",IF(I32=1,"Muy improbable",IF(I32=2,"Improbable",IF(I32=3,"Moderado",IF(I32=4,"Probable",IF(I32=5,"Casi certeza","")))))) -> Probable | K32: La comunicación remota con proveedores hace posible recibir mensajes de terceros que imiten su identidad. | L32: 3 | M32: Puede generar engaños, solicitudes falsas o decisiones basadas en una identidad fraudulenta. | N32: El engaño puede generar acciones o decisiones basadas en información falsa. | O32: {=IF(OR(I32="",L32=""),"",INDEX('Estimación de Severidad'!$O$11:$O$35,MATCH(1,('Estimación de Severidad'!$L$11:$L$35=I32)*('Estimación de Severidad'!$M$11:$M$35=L32),0)))} -> Alto
B37: Cobro de venta | C37: Recepción y verificación del comprobante de compra | D37: Cliente Vendedor | E37: Teléfono móvil WhatsApp | F37: Mostrar comprobante falso de compra al vendedor | G37: Pérdida económica | H37: Falta de verificación del comprobante. Falta de acreditación del dinero. | I37: 3 | J37: =IF(I37="","",IF(I37=1,"Muy improbable",IF(I37=2,"Improbable",IF(I37=3,"Moderado",IF(I37=4,"Probable",IF(I37=5,"Casi certeza","")))))) -> Moderado | K37: Existe la posibilidad de aceptar un comprobante adulterado si no se verifica la acreditación efectiva del pago antes de concretar la venta. | L37: 4 | M37: Puede provocar una pérdida directa de dinero al aceptar un pago inexistente. | N37: El negocio puede considerar una venta como pagada cuando el dinero nunca fue acreditado. | O37: {=IF(OR(I37="",L37=""),"",INDEX('Estimación de Severidad'!$O$11:$O$35,MATCH(1,('Estimación de Severidad'!$L$11:$L$35=I37)*('Estimación de Severidad'!$M$11:$M$35=L37),0)))} -> Extremo
B42: Cobro de venta | C42: Recepción y verificación del comprobante de compra | D42: Cliente Vendedor | E42: Télefono móvil WhatsApp | F42: Mostrar comprobante falso de compra al vendedor | G42: Pérdida de mercadería | H42: Falta de verificación del comprobante. Falta de acreditación del dinero. | I42: 3 | J42: =IF(I42="","",IF(I42=1,"Muy improbable",IF(I42=2,"Improbable",IF(I42=3,"Moderado",IF(I42=4,"Probable",IF(I42=5,"Casi certeza","")))))) -> Moderado | K42: La mercadería podría entregarse antes de confirmar el ingreso real del dinero, permitiendo que un comprobante falso pase inadvertido. | L42: 3 | M42: Puede ocasionar la entrega de productos sin recibir el pago correspondiente. | N42: La entrega sin cobro representa una pérdida directa de productos y valor económico. | O42: {=IF(OR(I42="",L42=""),"",INDEX('Estimación de Severidad'!$O$11:$O$35,MATCH(1,('Estimación de Severidad'!$L$11:$L$35=I42)*('Estimación de Severidad'!$M$11:$M$35=L42),0)))} -> Alto
B47: Gestión y registro en el sistema | C47: Registro y actualización de información en el sistema de gestión | D47: Vendedor | E47: PC Sistema de gestión | F47: Fallo en la infraestructura tecnológica que soporta el sistema | G47: Fallos de hardware | H47: Falta de manteniminento preventivo al equipo | I47: 4 | J47: =IF(I47="","",IF(I47=1,"Muy improbable",IF(I47=2,"Improbable",IF(I47=3,"Moderado",IF(I47=4,"Probable",IF(I47=5,"Casi certeza","")))))) -> Probable | K47: La PC se utiliza de manera habitual para el sistema de gestión y la falta de mantenimiento preventivo aumenta la posibilidad de fallas del equipo. | L47: 2 | M47: Puede dejar fuera de servicio la PC utilizada para la gestión. | N47: La PC es necesaria para el sistema de gestión y su falla puede detener parte de la operatoria. | O47: {=IF(OR(I47="",L47=""),"",INDEX('Estimación de Severidad'!$O$11:$O$35,MATCH(1,('Estimación de Severidad'!$L$11:$L$35=I47)*('Estimación de Severidad'!$M$11:$M$35=L47),0)))} -> Alto
B52: Gestión y registro en el sistema | C52: Registro y actualización de información en el sistema de gestión | D52: Vendedor | E52: PC Sistema de gestión | F52: Fallo en la infraestructura tecnológica que soporta el sistema | G52: Fallos de software | H52: Falta de parches y actualizaciones de seguridad | I52: 3 | J52: =IF(I52="","",IF(I52=1,"Muy improbable",IF(I52=2,"Improbable",IF(I52=3,"Moderado",IF(I52=4,"Probable",IF(I52=5,"Casi certeza","")))))) -> Moderado | K52: La falta de parches y actualizaciones puede favorecer errores o problemas de funcionamiento, aunque no necesariamente se presentan de forma frecuente. | L52: 4 | M52: Puede generar errores, bloqueos o indisponibilidad del sistema de gestión. | N52: Los errores del sistema pueden impedir registrar o consultar información necesaria para la gestión. | O52: {=IF(OR(I52="",L52=""),"",INDEX('Estimación de Severidad'!$O$11:$O$35,MATCH(1,('Estimación de Severidad'!$L$11:$L$35=I52)*('Estimación de Severidad'!$M$11:$M$35=L52),0)))} -> Extremo
B57: Gestión y registro en el sistema | C57: Registro y actualización de información en el sistema de gestión | D57: Vendedor | E57: PC Sistema de gestión | F57: Fallo en la infraestructura tecnológica que soporta el sistema | G57: Avería electrica | H57: Falta de protección eléctrica y de mecanismos de guardado o recuperación | I57: 3 | J57: =IF(I57="","",IF(I57=1,"Muy improbable",IF(I57=2,"Improbable",IF(I57=3,"Moderado",IF(I57=4,"Probable",IF(I57=5,"Casi certeza","")))))) -> Moderado | K57: Los cortes o variaciones de energía pueden producirse ocasionalmente y afectar el equipo o la información que se encuentre en uso. | L57: 2 | M57: Puede interrumpir el trabajo y provocar pérdida de información no guardada. | N57: Un corte puede interrumpir el trabajo y ocasionar pérdida de datos no guardados. | O57: {=IF(OR(I57="",L57=""),"",INDEX('Estimación de Severidad'!$O$11:$O$35,MATCH(1,('Estimación de Severidad'!$L$11:$L$35=I57)*('Estimación de Severidad'!$M$11:$M$35=L57),0)))} -> Moderado
B62: Comunicación vía móvil | C62: Gestión de comunicaciones comerciales mediante dispositivos móviles | D62: Vendedor | E62: Teléfono móvil WhatsApp Bussiness Whatsapp de Uso Personal | F62: Combinación de uso personal y comercial en los dispositivos | G62: Pérdida de información en cuentas personales | H62: Falta de backup en cuentas personales | I62: 5 | J62: =IF(I62="","",IF(I62=1,"Muy improbable",IF(I62=2,"Improbable",IF(I62=3,"Moderado",IF(I62=4,"Probable",IF(I62=5,"Casi certeza","")))))) -> Casi certeza | K62: Las cuentas personales se utilizan para comunicaciones comerciales y no cuentan con backup, aumentando considerablemente la exposición a pérdida de información. | L62: 3 | M62: Puede ocasionar la pérdida de conversaciones, pedidos o datos comerciales. | N62: La falta de respaldo puede hacer que conversaciones o datos comerciales no puedan recuperarse. | O62: {=IF(OR(I62="",L62=""),"",INDEX('Estimación de Severidad'!$O$11:$O$35,MATCH(1,('Estimación de Severidad'!$L$11:$L$35=I62)*('Estimación de Severidad'!$M$11:$M$35=L62),0)))} -> Extremo
B67: Comunicación vía móvil | C67: Gestión de comunicaciones comerciales mediante dispositivos móviles | D67: Vendedor | E67: Teléfono móvil WhatsApp Bussiness Whatsapp de Uso Personal | F67: Combinación de uso personal y comercial en los dispositivos | G67: Dificultad para recuperar conversaciones | H67: Ausencia de mecanismos de respaldo y recuperación de conversaciones | I67: 4 | J67: =IF(I67="","",IF(I67=1,"Muy improbable",IF(I67=2,"Improbable",IF(I67=3,"Moderado",IF(I67=4,"Probable",IF(I67=5,"Casi certeza","")))))) -> Probable | K67: La falta de mecanismos de respaldo y recuperación hace probable que existan dificultades para restaurar conversaciones ante una falla del dispositivo. | L67: 2 | M67: Puede dificultar la continuidad de la atención y recuperación de información previa. | N67: La falta de acceso a conversaciones anteriores puede complicar el seguimiento de pedidos o clientes. | O67: {=IF(OR(I67="",L67=""),"",INDEX('Estimación de Severidad'!$O$11:$O$35,MATCH(1,('Estimación de Severidad'!$L$11:$L$35=I67)*('Estimación de Severidad'!$M$11:$M$35=L67),0)))} -> Alto
B72: Comunicación vía móvil | C72: Gestión de comunicaciones comerciales mediante dispositivos móviles | D72: Vendedor | E72: Teléfono móvil WhatsApp Bussiness Whatsapp de Uso Personal | F72: Combinación de uso personal y comercial en los dispositivos | G72: Acceso no autorizado | H72: Falta de controles adecuados de acceso y autenticación en activos | I72: 1 | J72: =IF(I72="","",IF(I72=1,"Muy improbable",IF(I72=2,"Improbable",IF(I72=3,"Moderado",IF(I72=4,"Probable",IF(I72=5,"Casi certeza","")))))) -> Muy improbable | K72: Para concretarse, un tercero tendría que obtener acceso al dispositivo o superar los mecanismos de autenticación utilizados. | L72: 3 | M72: Puede exponer conversaciones, contactos o información comercial almacenada. | N72: El dispositivo contiene comunicaciones y datos que podrían quedar expuestos a terceros. | O72: {=IF(OR(I72="",L72=""),"",INDEX('Estimación de Severidad'!$O$11:$O$35,MATCH(1,('Estimación de Severidad'!$L$11:$L$35=I72)*('Estimación de Severidad'!$M$11:$M$35=L72),0)))} -> Moderado
B77: Comunicación vía móvil | C77: Gestión de comunicaciones comerciales mediante dispositivos móviles | D77: Vendedor | E77: Teléfono móvil WhatsApp Bussiness Whatsapp de Uso Personal | F77: Combinación de uso personal y comercial en los dispositivos | G77: Pérdida o hurto de dispositivos | H77: Ausencia de copias de seguridad, de un dispositivo alternativo y de un procedimiento de recuperación | I77: 3 | J77: =IF(I77="","",IF(I77=1,"Muy improbable",IF(I77=2,"Improbable",IF(I77=3,"Moderado",IF(I77=4,"Probable",IF(I77=5,"Casi certeza","")))))) -> Moderado | K77: Los teléfonos se utilizan de forma cotidiana y pueden extraviarse o ser sustraídos, aunque no es una situación que ocurra habitualmente. | L77: 5 | M77: Puede provocar pérdida de acceso a cuentas, información y comunicaciones del negocio. | N77: La pérdida física del equipo puede afectar tanto el acceso a cuentas como la continuidad de la comunicación comercial. | O77: {=IF(OR(I77="",L77=""),"",INDEX('Estimación de Severidad'!$O$11:$O$35,MATCH(1,('Estimación de Severidad'!$L$11:$L$35=I77)*('Estimación de Severidad'!$M$11:$M$35=L77),0)))} -> Extremo

Sheet Estimación de Probabilidad
B3: VALOR | C3: CATEGORÍA | D3: DESCRIPCIÓN
B5: 5 | C5: Casi certeza | D5: Riesgo cuya probabilidad de ocurrencia es muy alta, se tiene un alto grado de seguridad que este se presente en el año en curso. (90 % a 100 %).
B7: 4 | C7: Probable | D7: Riesgo cuya probabilidad de ocurrencia es alta, se tiene entre 66 % a 89 % de seguridad que este se presente en el año en curso.
B9: 3 | C9: Moderado | D9: Riesgo cuya probabilidad de ocurrencia es media, se tiene entre 31 % a 65 % de seguridad que este se presente en el año en curso.
B11: 2 | C11: Improbable | D11: Riesgo cuya probabilidad de ocurrencia es baja, se tiene entre 11 % a 30 % de seguridad que este se presente en el año en curso.
B13: 1 | C13: Muy improbable | D13: Riesgo cuya probabilidad de ocurrencia es muy baja, se tiene entre 1 % a 10 % de seguridad que este se presente en el año en curso.

Sheet Estimación de Impacto
B3: VALOR | C3: CATEGORÍA | D3: DESCRIPCIÓN
B5: 5 | C5: Catastrófico | D5: Riesgo cuya materialización puede generar pérdidas financieras ($) que tendrán un impacto catastrófico en la organización y/o comprometen totalmente la imagen de la organización.
B7: 4 | C7: Mayores | D7: Riesgo cuya materialización puede generar pérdidas financieras ($) que tendrán un impacto importante en la organización y/o comprometen fuertemente la imagen de la organización.
B9: 3 | C9: Moderadas | D9: Riesgo cuya materialización puede generar pérdidas financieras ($) que tendrán un impacto moderado en la organización y/o comprometen moderadamente la imagen de la organización.
B11: 2 | C11: Menores | D11: Riesgo cuya materialización puede generar pérdidas financieras ($) que tendrán un impacto menor en la organización y/o comprometen de forma menor la imagen de la organización.
B13: 1 | C13: Insignificantes | D13: Riesgo cuya materialización no genera pérdidas financieras ($) ni compromete de ninguna forma la imagen de la organización.

Sheet Estimación de Severidad
C3: Impacto | D3: 5
D4: 4
D5: 3
D6: 2
D7: 1
E8: 1 | F8: 2 | G8: 3 | H8: 4 | I8: 5
E10: Probabilidad | L10: Nivel de Probabilidad | M10: Nivel de Impacto | N10: Valor | O10: Severidad
L11: 5 | M11: 5 | N11: =L11*M11 -> 25 | O11: Extremo
L12: 5 | M12: 4 | N12: =L12*M12 -> 20 | O12: Extremo
L13: 5 | M13: 3 | N13: =L13*M13 -> 15 | O13: Extremo
L14: 5 | M14: 2 | N14: =L14*M14 -> 10 | O14: Alto
L15: 5 | M15: 1 | N15: =L15*M15 -> 5 | O15: Alto
L16: 4 | M16: 5 | N16: =L16*M16 -> 20 | O16: Extremo
L17: 4 | M17: 4 | N17: =L17*M17 -> 16 | O17: Extremo
L18: 4 | M18: 3 | N18: =L18*M18 -> 12 | O18: Alto
L19: 4 | M19: 2 | N19: =L19*M19 -> 8 | O19: Alto
L20: 4 | M20: 1 | N20: =L20*M20 -> 4 | O20: Moderado
L21: 3 | M21: 5 | N21: =L21*M21 -> 15 | O21: Extremo
L22: 3 | M22: 4 | N22: =L22*M22 -> 12 | O22: Extremo
... L35: 1 | M35: 1 | N35: =L35*M35 -> 1 | O35: Bajo

Sheet Tablas
A1: Probabilidad | B1: Impacto
A2: 1 | B2: 1
A3: 2 | B3: 2
A4: 3 | B4: 3
A5: 4 | B5: 4
A6: 5 | B6: 5
